sportybet.py
sportbet-1.0.0.dist-info/METADATA
sportbet-1.0.0.dist-info/WHEEL
sportbet-1.0.0.dist-info/top_level.txt
sportbet-1.0.0.dist-info/RECORD
